CanvasHacks/Configuration.py
CanvasHacks/ConsolidatedTextOutput.py
CanvasHacks/CredentialFields.py
CanvasHacks/DataManagement.py
CanvasHacks/DownloadProcessingTools.py
CanvasHacks/FileTools.py
CanvasHacks/GradingTools.py
CanvasHacks/InputFields.py
CanvasHacks/JournalsFileTools.py
CanvasHacks/JournalsTextTools.py
CanvasHacks/RequestTools.py
CanvasHacks/TextProcessing.py
CanvasHacks/TimeTools.py
CanvasHacks/UploadGradeTools.py
CanvasHacks/UrlTools.py
CanvasHacks/UtilityDecorators.py
CanvasHacks/VisualizationTools.py
CanvasHacks/__init__.py
CanvasHacks/environment.py
CanvasHacks/oathtest.py
CanvasHacks/testglobals.py
CanvasHacks/Api/DownloadProcessingTools.py
CanvasHacks/Api/RequestTools.py
CanvasHacks/Api/UploadGradeTools.py
CanvasHacks/Api/UrlTools.py
CanvasHacks/Api/__init__.py
CanvasHacks/DAOs/__init__.py
CanvasHacks/DAOs/mixins.py
CanvasHacks/DAOs/sqlite_dao.py
CanvasHacks/Definitions/__init__.py
CanvasHacks/Definitions/activity.py
CanvasHacks/Definitions/base.py
CanvasHacks/Definitions/discussion.py
CanvasHacks/Definitions/generic.py
CanvasHacks/Definitions/groups.py
CanvasHacks/Definitions/journal.py
CanvasHacks/Definitions/other.py
CanvasHacks/Definitions/skaa.py
CanvasHacks/Definitions/unit.py
CanvasHacks/Displays/__init__.py
CanvasHacks/Displays/dashboard.py
CanvasHacks/Errors/__init__.py
CanvasHacks/Errors/data_ingestion.py
CanvasHacks/Errors/grading.py
CanvasHacks/Errors/messaging.py
CanvasHacks/Errors/review_pairings.py
CanvasHacks/Files/FileTools.py
CanvasHacks/Files/FromDownloadFolder.py
CanvasHacks/Files/JournalsFileTools.py
CanvasHacks/Files/QuizReportFileTools.py
CanvasHacks/Files/__init__.py
CanvasHacks/GradingAnalyzers/__init__.py
CanvasHacks/GradingAnalyzers/blocked.py
CanvasHacks/GradingAnalyzers/nonempty.py
CanvasHacks/GradingCorrections/__init__.py
CanvasHacks/GradingCorrections/base.py
CanvasHacks/GradingCorrections/corrections.py
CanvasHacks/GradingCorrections/penalities.py
CanvasHacks/GradingHandlers/__init__.py
CanvasHacks-0.0.36.dist-info/LICENSE
CanvasHacks-0.0.36.dist-info/METADATA
CanvasHacks-0.0.36.dist-info/WHEEL
CanvasHacks-0.0.36.dist-info/top_level.txt
CanvasHacks-0.0.36.dist-info/RECORD
