Metadata-Version: 2.1
Name: CanvasHacks
Version: 0.0.36
Summary: Tools for mitigating the user-unfriendliness of canvas.
Home-page: https://github.com/AdamSwenson/CanvasHacks
Author: adam swenson
Author-email: adam.swenson@csun.edu
License: MIT
Platform: UNKNOWN
Classifier: License :: OSI Approved :: MIT License
Classifier: Programming Language :: Python
Classifier: Programming Language :: Python :: 3
Classifier: Programming Language :: Python :: 3.6
Classifier: Programming Language :: Python :: Implementation :: CPython
Classifier: Programming Language :: Python :: Implementation :: PyPy
Requires-Python: >=3.6.0
